{"component":2,"title":"「TypeScript」タグの一覧 - Tech SANDBOX","props":{"posts":[{"title":"【ES.next】Objectから任意のキーを削除した新しいObjectを作成する","slug":"remove-object-key","date":"2018-07-13","tags":["JavaScript","Babel","TypeScript"]},{"title":"React StaticでTypeScriptを使用した時のエラー対処法","slug":"webpacks-rules-in-static-config-js","date":"2018-07-03","tags":["ReactStatic","TypeScript","webpack"]},{"title":"ブログで使用した技術","slug":"use-technology","date":"2018-06-30","tags":["blog","React","preact","TypeScript","ReactStatic"]}],"tag":"TypeScript"}}